ad9361.py
pylibad9361-0.2.dist-info/METADATA
pylibad9361-0.2.dist-info/WHEEL
pylibad9361-0.2.dist-info/top_level.txt
pylibad9361-0.2.dist-info/RECORD
