Metadata-Version: 2.1
Name: pylibad9361
Version: 0.2
Summary: Device specific library for AD936X transceivers
Home-page: https://github.com/analogdevicesinc/libad9361
Maintainer: Analog Devices, Inc
Maintainer-email: travis.collins@analog.com
License: UNKNOWN
Platform: UNKNOWN
Classifier: Programming Language :: Python :: 3
Classifier: License :: OSI Approved :: GNU Lesser General Public License v2 or later (LGPLv2+)
Classifier: Operating System :: OS Independent
Requires-Python: >=3.6
Requires-Dist: pylibiio (==0.23.1)
